{
    "2": {
        "ЗФ-209-101-5-1": {
            "Баландина Екатерина": "Александровна",
            "Голубенко Екатерина": "Владимировна",
            "Кротова Жанна": "Викторовна",
            "Лясота Злата": "Васильевна",
            "Мухорина Софья": "Константиновна",
            "Сабурова Валерия": "Дмитриевна",
            "Семерикова Валентина": "Александровна",
            "Смирнова Елизавета": "Сергеевна",
            "Суворкина Валерия": "Вячеславовна",
            "Тумарова Софья": "Алексеевна",
            "Хасанова Валентина": "Геннадьевна",
            "Шакирова Фания": "Ильдаровна",
            "Ягольникова Дарья": "Алексеевна",
            "Ярина Светлана": "Александровна"
        },
        "ЗФ-209-100-3-1": {
            "Богусонова Эвелина": "Степановна",
            "Бочкарева Юлия": "Алексеевна",
            "Боярко Кристина": "Артемовна",
            "Буравцова Елена": "Сергеевна",
            "Еловикова Ангелина": "Евгеньевна",
            "Зеленкова Ксения": "Михайловна",
            "Калинковская Анна": "Александровна",
            "Лаврова Кира": "Алексеевна",
            "Лопан Ирина": "Юрьевна",
            "Музако Татьяна": "Владимировна",
            "Нажипова Гульшат": "Рушатовна",
            "Неверова Виктория": "Павловна",
            "Панина Елена": "Михайловна",
            "Парфенова Анастасия": "Сергеевна",
            "Примак Кристина": "Армиковна",
            "Садыкова Дарина": "Руслановна",
            "Салова Полина": "Владимировна",
            "Семенова Оксана": "Дмитриевна",
            "Смирнова Мария": "Юрьевна",
            "Столбикова Ольга": "Евгеньевна",
            "Тележкина Дарья": "Павловна",
            "Фомич София": "Михайловна",
            "Хохлева Елизавета": "Дмитриевна",
            "Чукавина София": "Александровна",
            "Шереметьева Елена": "Сергеевна"
        }
    },
    "1": {
        "Психопатология": {
            "Итоговый": "test1"
        }
    },
    "3": {
        "М": [],
        "Ж": [
            "Александровна",
            "Алексеевна",
            "Армиковна",
            "Артемовна",
            "Васильевна",
            "Викторовна",
            "Владимировна",
            "Вячеславовна",
            "Геннадьевна",
            "Дмитриевна",
            "Евгеньевна",
            "Ильдаровна",
            "Константиновна",
            "Михайловна",
            "Павловна",
            "Руслановна",
            "Рушатовна",
            "Сергеевна",
            "Степановна",
            "Юрьевна"
        ]
    }
}